beadsvec/__init__.py
beadsvec-4.0.0.dist-info/LICENSE
beadsvec-4.0.0.dist-info/METADATA
beadsvec-4.0.0.dist-info/WHEEL
beadsvec-4.0.0.dist-info/top_level.txt
beadsvec-4.0.0.dist-info/RECORD
