Metadata-Version: 2.1
Name: beadsvec
Version: 4.0.0
Summary: Beads vector notation package
Home-page: https://github.com/muzudho/beads-vector-notation
Author: muzudho
Author-email: muzudho1@gmail.com
Project-URL: Bug Tracker, https://github.com/muzudho/beads-vector-notation/issues
Classifier: Programming Language :: Python :: 3
Classifier: License :: OSI Approved :: MIT License
Classifier: Operating System :: OS Independent
Requires-Python: >=3.6
License-File: LICENSE
